omsdetector_forked/__init__.py
omsdetector_forked/atomic_parameters.py
omsdetector_forked/mof.py
omsdetector_forked/mof_collection.py
omsdetector_forked-2026.1.6.dist-info/LICENSE
omsdetector_forked-2026.1.6.dist-info/METADATA
omsdetector_forked-2026.1.6.dist-info/WHEEL
omsdetector_forked-2026.1.6.dist-info/RECORD
