Metadata-Version: 2.1
Name: omsdetector_forked
Version: 2026.1.6
Summary: Forked omsdetector to make it compliant with current python versions and dependencies
Author: Dinga Wonanke
Requires-Python: >=3.9,<4.0
Classifier: Programming Language :: Python :: 3
Classifier: Programming Language :: Python :: 3.9
Classifier: Programming Language :: Python :: 3.10
Classifier: Programming Language :: Python :: 3.11
Classifier: Programming Language :: Python :: 3.12
Requires-Dist: matplotlib (>=2.1.2)
Requires-Dist: pandas (>=1.3.5)
Requires-Dist: pymatgen (>2024.2.20)
